{
  "name": "Anusha Burnwal",
  "location": "Asansol, West Bengal, India",
  "bio": "I'm Anusha Burnwal a second year student currently pursuing BTech  in Information Technology, a UI/UX designer.",
  "avatar": "https://github.com/Anushaburnwal.png",
  "portfolio": "https://github.com/Anushaburnwal",
  "skills": [
    "C",
    "Python",
    "HTML",
    "CSS",
    "Web Development",
    "problems-solving",
    "Frontend",
    "Git",
    "GitHub",
    "problems-solving"
  ],
  "social": {
    "GitHub": "https://github.com/Anushaburnwal",
    "Twitter": "https://twitter.com/AnushaBurnwal",
    "LinkedIn": "https://www.linkedin.com/in/anusha-burnwal-91940728b"
  }
}
