{
  "name": "Darshan G K",
  "location": "Tumkur, India",
  "bio": "Python Developer and Open Source Contributor passionate about Machine Learning and innovative technologies.",
  "avatar": "https://github.com/imDarshanGK.png",
  "portfolio": "https://github.com/imDarshanGK",
  "skills": ["Python", "Machine Learning", "Open Source Contribution", "Git", "GitHub", "Streamlit"],
  "social": {
    "GitHub": "https://github.com/imDarshanGK",
    "Twitter": "https://x.com/imDarshanGK",
    "LinkedIn": "https://www.linkedin.com/in/imdarshangk",
    "Instagram": "https://www.instagram.com/i_am.d25",
    "Email": "darshanatmail@gmail.com"
  }
}
