{
  "name": "Mayur Raut",
  "location": "India",
  "bio": "Linux system admin and DevOps enthusiast focused on automation, server provisioning, and privacy-conscious cloud solutions.",
  "avatar": "https://github.com/razobeckett.png",
  "portfolio": "https://github.com/razobeckett",
  "skills": ["Go", "Ansible", "Bash Scripting", "Neovim", "Cloud Engineering", "Linux Administration"],
  "social": {
    "GitHub": "https://github.com/razobeckett",
    "Twitter": "https://twitter.com/razobeckett",
    "LinkedIn": "https://www.linkedin.com/in/mayurraut0"
  }
}
